manga_ar/MangaDL.py
manga_ar/__init__.py
manga_ar-0.0.2.dist-info/METADATA
manga_ar-0.0.2.dist-info/WHEEL
manga_ar-0.0.2.dist-info/top_level.txt
manga_ar-0.0.2.dist-info/RECORD
